saltext/apache/__init__.py
saltext/apache/version.py
saltext/apache/modules/__init__.py
saltext/apache/modules/apache.py
saltext/apache/modules/deb_apache.py
saltext/apache/modules/suse_apache.py
saltext/apache/states/__init__.py
saltext/apache/states/apache.py
saltext/apache/states/apache_conf.py
saltext/apache/states/apache_module.py
saltext/apache/states/apache_site.py
saltext_apache-1.0.1.dist-info/LICENSE
saltext_apache-1.0.1.dist-info/METADATA
saltext_apache-1.0.1.dist-info/NOTICE
saltext_apache-1.0.1.dist-info/WHEEL
saltext_apache-1.0.1.dist-info/entry_points.txt
saltext_apache-1.0.1.dist-info/top_level.txt
saltext_apache-1.0.1.dist-info/RECORD
